idex_sdk/__init__.py
idex_sdk/client/__init__.py
idex_sdk/client/order_book/__init__.py
idex_sdk/client/order_book/real_time.py
idex_sdk/client/order_book/utils.py
idex_sdk/client/rest/__init__.py
idex_sdk/client/rest/authenticated.py
idex_sdk/client/rest/public.py
idex_sdk/client/utils.py
idex_sdk/client/websocket/__init__.py
idex_sdk/client/websocket/client.py
idex_sdk/client/websocket/transform.py
idex_sdk/client/websocket/utils.py
idex_sdk/constants.py
idex_sdk/idex_types/__init__.py
idex_sdk/idex_types/enums.py
idex_sdk/idex_types/errors.py
idex_sdk/idex_types/order_book.py
idex_sdk/idex_types/rest/__init__.py
idex_sdk/idex_types/rest/guards.py
idex_sdk/idex_types/rest/request.py
idex_sdk/idex_types/rest/response.py
idex_sdk/idex_types/websocket/__init__.py
idex_sdk/idex_types/websocket/constants.py
idex_sdk/idex_types/websocket/guards.py
idex_sdk/idex_types/websocket/request.py
idex_sdk/idex_types/websocket/response.py
idex_sdk/order_book/__init__.py
idex_sdk/order_book/api_conversions.py
idex_sdk/order_book/hybrid.py
idex_sdk/order_book/quantities.py
idex_sdk/order_book/utils.py
idex_sdk/pipmath.py
idex_sdk/signatures.py
idex_sdk-1.0.0b2.dist-info/LICENSE
idex_sdk-1.0.0b2.dist-info/WHEEL
idex_sdk-1.0.0b2.dist-info/METADATA
idex_sdk-1.0.0b2.dist-info/RECORD
